{"data":{"markdownRemark":{"id":"6f11d351-1614-53b4-9b4d-af4788d26426","frontmatter":{"title":"카카오프렌즈 컬러링북 알고리즘 문제풀이 - 프로그래머스 Level 3 (테스트 O, 채점 X)"},"html":"<p>2017 카카오코드 예선 문제</p>\n<p>내가 생각한 문제 풀이들을 정리, 기록!</p>\n<h2 id=\"카카오프렌즈-컬러링북-문제\"><a href=\"#%EC%B9%B4%EC%B9%B4%EC%98%A4%ED%94%84%EB%A0%8C%EC%A6%88-%EC%BB%AC%EB%9F%AC%EB%A7%81%EB%B6%81-%EB%AC%B8%EC%A0%9C\" aria-label=\"카카오프렌즈 컬러링북 문제 permalink\" class=\"anchor\"><svg aria-hidden=\"true\" focusable=\"false\" height=\"16\" version=\"1.1\" viewBox=\"0 0 16 16\" width=\"16\"><path fill-rule=\"evenodd\" d=\"M4 9h1v1H4c-1.5 0-3-1.69-3-3.5S2.55 3 4 3h4c1.45 0 3 1.69 3 3.5 0 1.41-.91 2.72-2 3.25V8.59c.58-.45 1-1.27 1-2.09C10 5.22 8.98 4 8 4H4c-.98 0-2 1.22-2 2.5S3 9 4 9zm9-3h-1v1h1c1 0 2 1.22 2 2.5S13.98 12 13 12H9c-.98 0-2-1.22-2-2.5 0-.83.42-1.64 1-2.09V6.25c-1.09.53-2 1.84-2 3.25C6 11.31 7.55 13 9 13h4c1.45 0 3-1.69 3-3.5S14.5 6 13 6z\"></path></svg></a>카카오프렌즈 컬러링북 문제</h2>\n<blockquote>\n<p>문제설명과 제한사항은 다음의\n<a href=\"https://programmers.co.kr/learn/courses/30/lessons/1829\" target=\"_blank\">링크</a>에서 확인할 수 있습니다.</p>\n</blockquote>\n<h2 id=\"문제-해결-단계\"><a href=\"#%EB%AC%B8%EC%A0%9C-%ED%95%B4%EA%B2%B0-%EB%8B%A8%EA%B3%84\" aria-label=\"문제 해결 단계 permalink\" class=\"anchor\"><svg aria-hidden=\"true\" focusable=\"false\" height=\"16\" version=\"1.1\" viewBox=\"0 0 16 16\" width=\"16\"><path fill-rule=\"evenodd\" d=\"M4 9h1v1H4c-1.5 0-3-1.69-3-3.5S2.55 3 4 3h4c1.45 0 3 1.69 3 3.5 0 1.41-.91 2.72-2 3.25V8.59c.58-.45 1-1.27 1-2.09C10 5.22 8.98 4 8 4H4c-.98 0-2 1.22-2 2.5S3 9 4 9zm9-3h-1v1h1c1 0 2 1.22 2 2.5S13.98 12 13 12H9c-.98 0-2-1.22-2-2.5 0-.83.42-1.64 1-2.09V6.25c-1.09.53-2 1.84-2 3.25C6 11.31 7.55 13 9 13h4c1.45 0 3-1.69 3-3.5S14.5 6 13 6z\"></path></svg></a>문제 해결 단계</h2>\n<ol>\n<li>2차원 배열 picture의 각 요소를 탐방. (이중 for문)</li>\n<li>상하좌우의 색상이 현재 요소와 같은 색상이면 해당 방향으로 탐방.(재귀호출)</li>\n<li>이전에 탐방을 했으면 호출하지 않도록 방문여부 2차원 boolean배열 필요.</li>\n<li></li>\n<li>탐방시 </li>\n<li>탐방시 해당 영역을 탐방한 적이 있으면 0 리턴</li>\n<li>\n<p>상하좌우로 연결된 같은 색상의 공간을 영역으로.</p>\n<ul>\n<li></li>\n</ul>\n</li>\n<li>\n<p>2차원 배열 picture의 각 요소를 탐방.</p>\n<ul>\n<li></li>\n</ul>\n</li>\n<li>특정 요소로부터 시작해 상하좌우로 순회할 수 있도록 재귀호출을 사용.</li>\n<li>각 순회한 결과값으로 해당 영역의 사이즈 리턴.</li>\n<li></li>\n</ol>","headings":[{"value":"카카오프렌즈 컬러링북 문제","depth":2},{"value":"문제 해결 단계","depth":2}]}},"pageContext":{"isCreatedByStatefulCreatePages":false,"slug":"/posts/blog/algorithm/2019-04-10-카카오프렌즈컬러링북-알고리즘-문제풀이/","previous":null}}